CHANGELOG.md
LICENSE
README.md
rearq/__init__.py
rearq/cli.py
rearq/constants.py
rearq/enums.py
rearq/exceptions.py
rearq/server/__init__.py
rearq/server/app.py
rearq/server/depends.py
rearq/server/models.py
rearq/server/responses.py
rearq/server/routes/__init__.py
rearq/server/routes/index.py
rearq/server/routes/job.py
rearq/server/routes/result.py
rearq/server/routes/task.py
rearq/server/routes/worker.py
rearq/server/schemas.py
rearq/server/static/favicon.svg
rearq/server/static/index.css
rearq/server/templates/base.html
rearq/server/templates/dashboard.html
rearq/server/templates/job.html
rearq/server/templates/result.html
rearq/server/templates/task.html
rearq/server/templates/widgets/formatters.html
rearq/server/templates/widgets/task_actions.html
rearq/server/templates/worker.html
rearq/signals.py
rearq/task.py
rearq/utils.py
rearq/version.py
rearq/worker.py
rearq-0.2.9.dist-info/LICENSE
rearq-0.2.9.dist-info/METADATA
rearq-0.2.9.dist-info/WHEEL
rearq-0.2.9.dist-info/entry_points.txt
rearq-0.2.9.dist-info/RECORD
