Metadata-Version: 2.1
Name: rearq
Version: 0.2.9
Summary: A distributed task queue built with asyncio and redis, with built-in web interface
Home-page: https://github.com/long2ice/rearq.git
License: Apache-2.0
Keywords: asyncio,task,arq,queue,distributed
Author: long2ice
Author-email: long2ice@gmail.com
Requires-Python: >=3.8,<4.0
Classifier: License :: OSI Approved :: Apache Software License
Classifier: Programming Language :: Python :: 3
Classifier: Programming Language :: Python :: 3.8
Classifier: Programming Language :: Python :: 3.9
Classifier: Programming Language :: Python :: 3.10
Classifier: Programming Language :: Python :: 3.11
Classifier: Programming Language :: Python :: 3.12
Provides-Extra: mysql
Provides-Extra: postgres
Requires-Dist: aiofiles
Requires-Dist: asyncmy (>=0.2.8,<0.3.0) ; extra == "mysql"
Requires-Dist: asyncpg ; extra == "postgres"
Requires-Dist: click
Requires-Dist: crontab
Requires-Dist: fastapi[all]
Requires-Dist: loguru
Requires-Dist: redis (>=4.2.0rc1,<5.0.0)
Requires-Dist: tortoise-orm (>=0.20.0,<0.21.0)
Project-URL: Documentation, https://github.com/long2ice/rearq/blob/master/README.md
Project-URL: Repository, https://github.com/long2ice/rearq.git
